[
  {
    "id": 1,
    "title": "Lyxlägenhet med älvutsikt",
    "area": "Lindholmen",
    "address": "Lindholmspiren 4",
    "price_per_night": 1850,
    "bedrooms": 3,
    "bathrooms": 2,
    "max_persons": 6,
    "amenities": [
      "Wifi",
      "Parkering",
      "Kök",
      "Diskmaskin",
      "TV",
      "Balkong",
      "Tvättmaskin"
    ],
    "description": "Spektakulär lägenhet med panoramautsikt. Perfekt för ledningsgrupper.",
    "image_url": "https://images.unsplash.com/photo-1600607687939-ce8a6c25118c?w=800&q=80&auto=format",
    "rating": 4.97,
    "reviews_count": 43,
    "is_available": true,
    "badge": "Populär"
  },
  {
    "id": 2,
    "title": "Design-svit i Haga",
    "area": "Haga",
    "address": "Haga Nygata 22",
    "price_per_night": 1250,
    "bedrooms": 2,
    "bathrooms": 1,
    "max_persons": 4,
    "amenities": [
      "Wifi",
      "Kök",
      "TV",
      "Cykelförvaring"
    ],
    "description": "Välrenoverad 1800-talsfastighet med moderna bekvämligheter.",
    "image_url": "https://images.unsplash.com/photo-1502672260266-1c1ef2d93688?w=800&q=80&auto=format",
    "rating": 4.89,
    "reviews_count": 67,
    "is_available": true,
    "badge": "Toppbetyg"
  },
  {
    "id": 3,
    "title": "Minimalistisk studio, Avenyn",
    "area": "Avenyn",
    "address": "Kungsportsavenyn 18",
    "price_per_night": 950,
    "bedrooms": 1,
    "bathrooms": 1,
    "max_persons": 2,
    "amenities": [
      "Wifi",
      "Kök",
      "Gymaccess"
    ],
    "description": "Modern studio med direkt access till Avenyn.",
    "image_url": "https://images.unsplash.com/photo-1522708323590-d24dbb6b0267?w=800&q=80&auto=format",
    "rating": 4.82,
    "reviews_count": 91,
    "is_available": true,
    "badge": null
  },
  {
    "id": 4,
    "title": "Strandnära villa, Majorna",
    "area": "Majorna",
    "address": "Karl Johansgatan 55",
    "price_per_night": 2200,
    "bedrooms": 4,
    "bathrooms": 2,
    "max_persons": 8,
    "amenities": [
      "Wifi",
      "Parkering",
      "Kök",
      "Trädgård",
      "Terrass"
    ],
    "description": "Rymlig villa i Majornas kulturkvarter med privat trädgård.",
    "image_url": "https://images.unsplash.com/photo-1564013799919-ab600027ffc6?w=800&q=80&auto=format",
    "rating": 4.95,
    "reviews_count": 28,
    "is_available": true,
    "badge": "Nytt"
  },
  {
    "id": 5,
    "title": "Executive-lägenhet, Vasastan",
    "area": "Vasastan",
    "address": "Vasagatan 40",
    "price_per_night": 1450,
    "bedrooms": 2,
    "bathrooms": 2,
    "max_persons": 4,
    "amenities": [
      "Wifi",
      "Kök",
      "Arbetsplats",
      "TV",
      "Tvättmaskin"
    ],
    "description": "Elegant lägenhet nära Chalmers och Handelshögskolan.",
    "image_url": "https://images.unsplash.com/photo-1493809842364-78817add7ffb?w=800&q=80&auto=format",
    "rating": 4.78,
    "reviews_count": 55,
    "is_available": true,
    "badge": null
  },
  {
    "id": 6,
    "title": "Penthouse med takterrass",
    "area": "Eriksberg",
    "address": "Eriksberg Allé 8",
    "price_per_night": 2800,
    "bedrooms": 3,
    "bathrooms": 2,
    "max_persons": 6,
    "amenities": [
      "Wifi",
      "Takterrass",
      "Parkering",
      "Kök",
      "Hushållerska",
      "Gym"
    ],
    "description": "Exklusivt penthouse med 180° utsikt. Hushållerska ingår.",
    "image_url": "https://images.unsplash.com/photo-1600596542815-ffad4c1539a9?w=800&q=80&auto=format",
    "rating": 5,
    "reviews_count": 19,
    "is_available": true,
    "badge": "Exklusiv"
  },
  {
    "id": 7,
    "title": "Centralt läge, Centrum",
    "area": "Centrum",
    "address": "Drottninggatan 10",
    "price_per_night": 1100,
    "bedrooms": 2,
    "bathrooms": 1,
    "max_persons": 4,
    "amenities": [
      "Wifi",
      "Kök",
      "TV",
      "Hiss"
    ],
    "description": "Centralt belägen, gångavstånd till allt.",
    "image_url": "https://images.unsplash.com/photo-1560448204-e02f11c3d0e2?w=800&q=80&auto=format",
    "rating": 4.71,
    "reviews_count": 108,
    "is_available": true,
    "badge": null
  },
  {
    "id": 8,
    "title": "Tech-hub, Johanneberg",
    "area": "Johanneberg",
    "address": "Eklandagatan 25",
    "price_per_night": 1350,
    "bedrooms": 3,
    "bathrooms": 2,
    "max_persons": 5,
    "amenities": [
      "Wifi 1Gbit",
      "Arbetsplatser",
      "Whiteboardvägg",
      "Kök",
      "Parkering"
    ],
    "description": "Designad för teknikteam. 1Gbit fiber, dubbla skärmar ingår.",
    "image_url": "https://images.unsplash.com/photo-1484154218962-a197022b5858?w=800&q=80&auto=format",
    "rating": 4.91,
    "reviews_count": 34,
    "is_available": true,
    "badge": "Tech"
  }
]